tg/__init__.py
tg/__main__.py
tg/colors.py
tg/config.py
tg/controllers.py
tg/models.py
tg/msg.py
tg/resources/tg.png
tg/tdlib.py
tg/update_handlers.py
tg/utils.py
tg/views.py
tg-0.22.0.dist-info/METADATA
tg-0.22.0.dist-info/WHEEL
tg-0.22.0.dist-info/RECORD
